MANIFEST.in
setup.py
sunscreen_py/__init__.py
sunscreen_py.egg-info/PKG-INFO
sunscreen_py.egg-info/SOURCES.txt
sunscreen_py.egg-info/dependency_links.txt
sunscreen_py.egg-info/requires.txt
sunscreen_py.egg-info/top_level.txt
sunscreen_py/base/__init__.py
sunscreen_py/base/buffer.py
sunscreen_py/base/context.py
sunscreen_py/base/encrypted.py
sunscreen_py/base/encryptedfloat64.py
sunscreen_py/base/encryptedfloatarray.py
sunscreen_py/base/encryptedsigned.py
sunscreen_py/base/encryptedunsigned256.py
sunscreen_py/base/encryptedunsigned64.py
sunscreen_py/base/rustlibrary.py
sunscreen_py/c_libs/__init__.py
sunscreen_py/c_libs/linux.so
sunscreen_py/c_libs/osx.dylib
sunscreen_py/c_libs/__pycache__/__init__.cpython-311.pyc
sunscreen_py/internal/__init__.py
sunscreen_py/internal/sunscreenpool.py
sunscreen_py/torch/__init__.py
sunscreen_py/torch/encryptedconv2d.py
sunscreen_py/torch/encrypteddropout.py
sunscreen_py/torch/encryptedlinear.py
sunscreen_py/torch/encryptedrelu.py
sunscreen_py/torch/encryptedsigmoid.py
sunscreen_py/torch/encryptedtanh.py
sunscreen_py/torch/encryptedtensor.py