Metadata-Version: 2.1
Name: sunscreen-py
Version: 0.0.4
Summary: Sunscreen Python Interop Package
Author: SmartFHE
Author-email: hello@sunscreen.tch
Keywords: cryptography,sunscreen,fhe,bfv,web3
